setup.py
Django_Next_Please.egg-info/PKG-INFO
Django_Next_Please.egg-info/SOURCES.txt
Django_Next_Please.egg-info/dependency_links.txt
Django_Next_Please.egg-info/top_level.txt
NextPlease/__init__.py