Metadata-Version: 1.0
Name: Django-Next-Please
Version: 12.06.1
Summary: Simple Pagination Decorator for Django.
Home-page: https://github.com/pizzapanther/Django-Next-Please
Author: Paul Bailey
Author-email: paul.m.bailey@gmail.com
License: BSD
Platform: UNKNOWN
